<?xml version='1.0' encoding='UTF-8'?>
<tv>
  <channel id="C23.api.telerama.fr">
    <display-name>één</display-name>
    <icon src="https://television.telerama.fr/sites/tr_master/files/sheet_media/tv/500x500/23.png" />
  </channel>
  <channel id="C50.api.telerama.fr">
    <display-name>Club RTL</display-name>
    <icon src="https://television.telerama.fr/sites/tr_master/files/sheet_media/tv/500x500/50.png" />
  </channel>
  <channel id="C164.api.telerama.fr">
    <display-name>La Une</display-name>
    <icon src="https://television.telerama.fr/sites/tr_master/files/sheet_media/tv/500x500/164.png" />
  </channel>
  <channel id="C168.api.telerama.fr">
    <display-name>RTL TVI</display-name>
    <icon src="https://television.telerama.fr/sites/tr_master/files/sheet_media/tv/500x500/168.png" />
  </channel>
  <channel id="C187.api.telerama.fr">
    <display-name>La Deux</display-name>
    <icon src="https://television.telerama.fr/sites/tr_master/files/sheet_media/tv/500x500/187.png" />
  </channel>
  <channel id="C377.api.telerama.fr">
    <display-name>Plug RTL</display-name>
    <icon src="https://television.telerama.fr/sites/tr_master/files/sheet_media/tv/500x500/377.png" />
  </channel>
  <channel id="C892.api.telerama.fr">
    <display-name>La Trois</display-name>
    <icon src="https://television.telerama.fr/sites/tr_master/files/sheet_media/tv/500x500/892.png" />
  </channel>
  <channel id="C1280.api.telerama.fr">
    <display-name>Ketnet</display-name>
    <icon src="https://television.telerama.fr/sites/tr_master/files/sheet_media/tv/500x500/1280.png" />
  </channel>
  <programme start="20250702233100" channel="C164.api.telerama.fr" stop="20250703000500">
    <title>JT 19h30</title>
    <desc lang="fr">Tous les jours, le JT de 19h30 informe de l'actualité et des faits de société, politiques, économiques, culturels et sportifs.</desc>
    <category lang="fr">journal</category>
    <length units="minutes">34</length>
    <icon src="https://focus.telerama.fr/1111x625/2023/03/27/1ea365609cb17d38273a87775fb636b820f7f0c7_7EC349D60DB870D61449E7958443756B.jpg" />
    <previously-shown />
    <rating system="CSA">
      <value>Tout public</value>
    </rating>
  </programme>
  <programme start="20250703000500" channel="C164.api.telerama.fr" stop="20250703000700">
    <title>Air de familles</title>
    <desc lang="fr">Pour mieux faire connaître aux familles les services gratuits que l'ONE met à leur disposition mais aussi les informer à propos de la santé et de l'éducation des enfants.</desc>
    <category lang="fr">magazine de société</category>
    <length units="minutes">2</length>
    <icon src="https://focus.telerama.fr/1111x625/2021/08/30/0522ba79f4bde957496a945a69106e317d49e0c9.jpg" />
    <rating system="CSA">
      <value>Tout public</value>
    </rating>
  </programme>
  <programme start="20250703000700" channel="C164.api.telerama.fr" stop="20250703001800">
    <title>Quel temps pour la planète</title>
    <desc lang="fr">En 11 minutes et 30 secondes, un panorama complet des phénomènes météo, de l'évolution du climat, et des initiatives positives pour un avenir durable.</desc>
    <category lang="fr">magazine de la nature</category>
    <length units="minutes">11</length>
    <icon src="https://focus.telerama.fr/1111x625/2024/12/25/0371a730f2bc4b859d1047fcc3144895.jpg" />
    <previously-shown />
    <rating system="CSA">
      <value>Tout public</value>
    </rating>
  </programme>
  <programme start="20250703001800" channel="C164.api.telerama.fr" stop="20250703002100">
    <title>Météo 20h00</title>
    <desc lang="fr">Le bulletin météo du soir.</desc>
    <category lang="fr">météo</category>
    <length units="minutes">3</length>
    <icon src="https://focus.telerama.fr/1111x625/2025/02/26/77b8aa883fb34b089662a80507e0c4d1.jpg" />
    <previously-shown />
    <rating system="CSA">
      <value>Tout public</value>
    </rating>
  </programme>
  <programme start="20250703002100" channel="C164.api.telerama.fr" stop="20250703035900">
    <title>JT 19h30</title>
    <desc lang="fr">Tous les jours, le JT de 19h30 informe de l'actualité et des faits de société, politiques, économiques, culturels et sportifs.</desc>
    <category lang="fr">journal</category>
    <length units="minutes">218</length>
    <icon src="https://focus.telerama.fr/1111x625/2023/03/27/1ea365609cb17d38273a87775fb636b820f7f0c7_7EC349D60DB870D61449E7958443756B.jpg" />
    <previously-shown />
    <rating system="CSA">
      <value>Tout public</value>
    </rating>
  </programme>
  <programme start="20250703035900" channel="C164.api.telerama.fr" stop="20250703060000">
    <title>Le 6-8</title>
    <desc lang="fr">Très interactive, l'émission est animée par Sara De Paduwa. Au sommaire: de l'info, le journal des sports, l'info-trafic, des reportages, ainsi que des chroniques de la vie quotidienne: les Buzz; Nos amis les animaux; Sexo; On s'bouge!; Beauté, mode &amp; bien-être; La télé d'avant; G testé pour vous; People; Enfants; Sport extrêmes; Un p'tit bout d'histoire et des News musicales.</desc>
    <category lang="fr">magazine de services</category>
    <length units="minutes">121</length>
    <icon src="https://focus.telerama.fr/1111x625/2023/04/03/237eee38ef4308aa05522aeb05a252a8968f16ef_4A95F84DD81BA45175D5A77F481BFE86.jpg" />
    <new />
    <rating system="CSA">
      <value>Tout public</value>
    </rating>
  </programme>
  <programme start="20250703060000" channel="C164.api.telerama.fr" stop="20250703070000">
    <title>Le 8-9</title>
    <desc lang="fr">Humour, info régionale, nationale et internationale, invités, météo, info-services, billets d'humeur... Au sommaire, le grand journal de 8h, le billet d'humeur de Jérôme De Warzée, le journal régional, les chroniques, l'interview d'un invité qui fait l'actualité culturelle et...Le qui ka?</desc>
    <category lang="fr">magazine de services</category>
    <length units="hours">1</length>
    <icon src="https://focus.telerama.fr/1111x625/2021/10/11/7aa849d7a8c6541c01af67deaacf8ee08ac72ff1.jpg" />
    <premiere />
    <new />
    <rating system="CSA">
      <value>Tout public</value>
    </rating>
  </programme>
  <programme start="20250703070000" channel="C164.api.telerama.fr" stop="20250703090200">
    <title>Le 8-9 continue</title>
    <desc lang="fr">Animé par Cyril entouré d'Alyssia Delré et François Denamur, Le 8/9 continue tout au long de l'été sur VivaCité, de 9h à 11h. Chaque jour un artiste belge en live, des jeux, des chroniques musique, culture, bien-être, cuisine,...et beaucoup de bonne humeur.</desc>
    <category lang="fr">divertissement</category>
    <length units="minutes">122</length>
    <icon src="https://focus.telerama.fr/1111x625/2021/12/13/b03f3db82828a32c7269293e829f4196c1fd880f_3C91286C4EF207A513B22402BBF8D48C.jpg" />
    <premiere />
    <new />
    <rating system="CSA">
      <value>Tout public</value>
    </rating>
  </programme>
  <programme start="20250703090200" channel="C164.api.telerama.fr" stop="20250703092100">
    <title>On n'est pas des pigeons - express</title>
    <desc lang="fr">Présenté par Fanny Jandrain et Thibaut Roland, "On n'est pas des pigeons" décrypte les codes de la consommation et du marketing pour que chacun puisse faire son choix sans se faire "pigeonner". Les chroniqueurs dénichent les arnaques et les bons plans, et vous aident à boucler vos fins de mois.</desc>
    <category lang="fr">divertissement</category>
    <length units="minutes">19</length>
    <icon src="https://focus.telerama.fr/1111x625/2024/04/10/b217174ebed84965a41daa81d7eac439.jpg" />
    <rating system="CSA">
      <value>Tout public</value>
    </rating>
  </programme>
  <programme start="20250703092100" channel="C164.api.telerama.fr" stop="20250703095700">
    <title>Demain nous appartient</title>
    <desc lang="fr">Saison:8 - Episode:1979 - Mélody trahit un ami proche, malgré elle. Alex prend un malin plaisir à piéger Kevin. Karim déclare son amour à Rayane, qui prend son envol.</desc>
    <credits>
      <director>Dyna Gauzy</director>
      <director>Alexis Charrier</director>
      <director>David Lanzmann</director>
      <director>Nicolas Herdt</director>
      <director>Yann Elmosnino</director>
      <director>Sophie Vigneu</director>
      <director>Marc Atgé</director>
      <director>Martin Day</director>
      <actor>Jennifer Lauret</actor>
      <actor>Ingrid Chauvin</actor>
      <actor>Xavier Deluc</actor>
      <actor>Alexandre Brasseur</actor>
      <actor>Emmanuel Moire</actor>
      <actor>Samy Gharbi</actor>
      <actor>Charlotte Gaccio</actor>
      <actor>Franck Monsigny</actor>
      <actor>Hébert Solène</actor>
    </credits>
    <category lang="fr">série dramatique</category>
    <length units="minutes">36</length>
    <icon src="https://focus.telerama.fr/1111x625/2023/02/13/a38c31ad93511b4f10a5c9bf0e502e16cab7d716_0CB6B72D976D814E63DA378960E3D397.jpg" />
    <episode-num system="xmltv_ns">7.1978.</episode-num>
    <previously-shown />
    <rating system="CSA">
      <value>Tout public</value>
    </rating>
  </programme>
  <programme start="20250703095700" channel="C164.api.telerama.fr" stop="20250703104100">
    <title>Les Feux de l'amour</title>
    <desc lang="fr">Abby assiste à la visite de Tucker qui est venu voir Dominic et lui pose certaines questions pour savoir s'il a changé. Elle se méfie de lui mais accepte néanmoins qu'il voie régulièrement Dominic. Diane est revenue à Genoa, au désespoir d'Ashley et Phyllis. Summer tente de renouer avec sa mère, mais Phyllis refuse de lui parler. Diane évoque son plan pour séduire Jeremy à Jack et Kyle qui sont inquiets pour elle mais décident de la soutenir. Elle décide de retourner dans sa suite au Grand Phénix. Summer parle à Danny de ses difficultés actuelles. Danny lui conseille de ne pas mentir à Kyle, même par omission. Tucker rend visite à Diane pour savoir quand Jeremy Stark quitte la ville. Elle en profite pour régler ses comptes avec lui...</desc>
    <category lang="fr">feuilleton sentimental</category>
    <length units="minutes">44</length>
    <icon src="https://focus.telerama.fr/1111x625/2025/02/27/79aeb6440b0e4862ab0b433035876550.jpg" />
    <rating system="CSA">
      <value>Tout public</value>
    </rating>
  </programme>
  <programme start="20250703104100" channel="C164.api.telerama.fr" stop="20250703105300">
    <title>Quel temps pour la planète</title>
    <desc lang="fr">En 11 minutes et 30 secondes, un panorama complet des phénomènes météo, de l'évolution du climat, et des initiatives positives pour un avenir durable.</desc>
    <category lang="fr">magazine de la nature</category>
    <length units="minutes">12</length>
    <icon src="https://focus.telerama.fr/1111x625/2024/12/25/0371a730f2bc4b859d1047fcc3144895.jpg" />
    <rating system="CSA">
      <value>Tout public</value>
    </rating>
  </programme>
  <programme start="20250703105300" channel="C164.api.telerama.fr" stop="20250703105800">
    <title>Météo 12h50</title>
    <category lang="fr">météo</category>
    <length units="minutes">5</length>
    <icon src="https://focus.telerama.fr/1111x625/2025/02/26/77b8aa883fb34b089662a80507e0c4d1.jpg" />
    <rating system="CSA">
      <value>Tout public</value>
    </rating>
  </programme>
  <programme start="20250703105800" channel="C164.api.telerama.fr" stop="20250703112600">
    <title>JT 13h (La Une)</title>
    <desc lang="fr">Le Journal télévisé de 13 heures par toute la rédaction de la chaîne.</desc>
    <category lang="fr">journal</category>
    <length units="minutes">28</length>
    <icon src="https://focus.telerama.fr/1111x625/2025/02/26/2af0837d9fb648019f5497a917f08316.jpg" />
    <new />
    <rating system="CSA">
      <value>Tout public</value>
    </rating>
  </programme>
  <programme start="20250703112600" channel="C164.api.telerama.fr" stop="20250703113100">
    <title>Alors on sort ?</title>
    <desc lang="fr">L'émission met à l'honneur les régions, leurs habitants, leurs langues régionales et leur humour. Un moment privilégié de proximité présenté par Fanny Jandrain, en compagnie d'un invité.</desc>
    <category lang="fr">magazine culturel</category>
    <length units="minutes">5</length>
    <icon src="https://focus.telerama.fr/1111x625/2024/05/15/9957f1735ab64048a01d72209daf79e6.jpg" />
    <rating system="CSA">
      <value>Tout public</value>
    </rating>
  </programme>
  <programme start="20250703113100" channel="C164.api.telerama.fr" stop="20250703113700">
    <title>Météo 13h30</title>
    <category lang="fr">météo</category>
    <length units="minutes">6</length>
    <icon src="https://focus.telerama.fr/1111x625/2025/05/14/827f285a741a4a0e838e85904a262af9.jpg" />
    <rating system="CSA">
      <value>Tout public</value>
    </rating>
  </programme>
  <programme start="20250703113700" channel="C164.api.telerama.fr" stop="20250703122300">
    <title>Affaire conclue, tout le monde a quelque chose à vendre</title>
    <desc lang="fr">Parce que les maisons sont remplies de babioles insolites qui ne demandent qu'à trouver acquéreurs, des spécialistes accompagnent les propriétaires d'objets tout au long des étapes susceptibles de les mener à la vente.</desc>
    <category lang="fr">magazine de l'art de vivre</category>
    <length units="minutes">46</length>
    <icon src="https://focus.telerama.fr/1111x625/2025/05/29/bc1cf844435940eb9d8ea8046f6300fe.jpg" />
    <rating system="CSA">
      <value>Tout public</value>
    </rating>
  </programme>
  <programme start="20250703122300" channel="C164.api.telerama.fr" stop="20250703131000">
    <title>Affaire conclue, tout le monde a quelque chose à vendre</title>
    <desc lang="fr">Parce que les maisons sont remplies de babioles insolites qui ne demandent qu'à trouver acquéreurs, des spécialistes accompagnent les propriétaires d'objets tout au long des étapes susceptibles de les mener à la vente.</desc>
    <category lang="fr">magazine de l'art de vivre</category>
    <length units="minutes">47</length>
    <icon src="https://focus.telerama.fr/1111x625/2025/05/29/bc1cf844435940eb9d8ea8046f6300fe.jpg" />
    <rating system="CSA">
      <value>Tout public</value>
    </rating>
  </programme>
  <programme start="20250703131000" channel="C164.api.telerama.fr" stop="20250703151300">
    <title>Diane, femme flic</title>
    <sub-title>Voir Bollywood et mourir</sub-title>
    <desc lang="fr">Saison:7 - Episode:8 - Anoki Kalampur, la tête d'affiche d'un spectacle bollywoodien sur une scène parisienne, est retrouvée morte la veille de la première. Son corps reposait sur un bûcher dressé dans la forêt d'Eudon. Le mode opératoire ressemble étrangement à celui du meurtre d'un chanteur indien, commis quelques semaines plus tôt. Diane Carro est chargée de l'enquête sur ces deux morts mystérieuses, qui touchent une communauté qu'elle ne connaît pas bien. Pour résoudre cette affaire, la policière et son équipe doivent s'immerger dans la culture indienne et dépasser leurs préjugés...</desc>
    <credits>
      <director>Nicolas Herdt</director>
      <actor>Jean-Yves Berteloot</actor>
      <actor>Isabel Otero</actor>
      <actor>Alexandre Brasseur</actor>
      <actor>Magaly Godenaire</actor>
      <actor>Joël Zaffarano</actor>
      <actor>Hugo Brunswick</actor>
      <actor>Audrey Caillaud</actor>
      <actor>Emilie Chesnais</actor>
      <actor>Koubba Hassan</actor>
      <actor>Gilian Petrovski</actor>
      <actor>Matthieu Dessertine</actor>
      <actor>Silvie Laguna</actor>
      <writer>Mora Pierre-Yves</writer>
      <writer>Vincent Robert</writer>
      <writer>Herry-Leclerc Angèle</writer>
      <writer>Marie Guilmineau</writer>
    </credits>
    <date>2010</date>
    <category lang="fr">série policière</category>
    <length units="minutes">123</length>
    <icon src="https://focus.telerama.fr/1111x625/2025/04/23/9d219a9ce56840888663b0955d9d3f6b.jpg" />
    <episode-num system="xmltv_ns">6.7.</episode-num>
    <rating system="CSA">
      <value>Tout public</value>
    </rating>
  </programme>
  <programme start="20250703151300" channel="C164.api.telerama.fr" stop="20250703151600">
    <title>Alors on sort ?</title>
    <desc lang="fr">L'émission met à l'honneur les régions, leurs habitants, leurs langues régionales et leur humour. Un moment privilégié de proximité présenté par Fanny Jandrain, en compagnie d'un invité.</desc>
    <category lang="fr">magazine culturel</category>
    <length units="minutes">3</length>
    <icon src="https://focus.telerama.fr/1111x625/2024/05/15/9957f1735ab64048a01d72209daf79e6.jpg" />
    <previously-shown />
    <rating system="CSA">
      <value>Tout public</value>
    </rating>
  </programme>
  <programme start="20250703151600" channel="C164.api.telerama.fr" stop="20250703152000">
    <title>Météo 19h25</title>
    <desc lang="fr">Tout au long de la journée, les prévisions météorologiques nationales et les bons conseils pour ne pas être surpris par le temps.</desc>
    <category lang="fr">météo</category>
    <length units="minutes">4</length>
    <icon src="https://focus.telerama.fr/1111x625/2025/05/14/827f285a741a4a0e838e85904a262af9.jpg" />
    <rating system="CSA">
      <value>Tout public</value>
    </rating>
  </programme>
  <programme start="20250703152000" channel="C164.api.telerama.fr" stop="20250703155200">
    <title>Red Flames</title>
    <category lang="fr">sport : football</category>
    <length units="minutes">32</length>
    <icon src="https://focus.telerama.fr/1111x625/2025/06/25/a37bd54f25c340cfb907066edee2a0f8.jpg" />
    <rating system="CSA">
      <value>Tout public</value>
    </rating>
  </programme>
  <programme start="20250703155200" channel="C164.api.telerama.fr" stop="20250703180000">
    <title>Football : Euro féminin</title>
    <desc lang="fr">Les Red Flames débutent leur Euro en affrontant les Italiennes au stade du Tourbillon, à Sion. Quarts de finaliste en 2022, les joueuses belges vont tenter de faire aussi bien, sinon mieux, cette année en Suisse. Pour cela, il leur faudra prendre l'une des premières places du groupe B au sein duquel elles devront également affronter l'Espagne et le Portugal. Finalistes en 1993 et 1997, les Italiennes n'ont pas passé le premier tour, lors des deux dernières éditions de l'Euro.</desc>
    <category lang="fr">sport : football</category>
    <length units="minutes">128</length>
    <icon src="https://focus.telerama.fr/1111x625/2025/06/19/a175301ac2da405db4f493b77df03a75.jpg" />
    <new />
    <rating system="CSA">
      <value>Tout public</value>
    </rating>
  </programme>
  <programme start="20250703180000" channel="C164.api.telerama.fr" stop="20250703184500">
    <title>JT 19h30</title>
    <desc lang="fr">Tous les jours, le JT de 19h30 informe de l'actualité et des faits de société, politiques, économiques, culturels et sportifs.</desc>
    <category lang="fr">journal</category>
    <length units="minutes">45</length>
    <icon src="https://focus.telerama.fr/1111x625/2023/03/27/1ea365609cb17d38273a87775fb636b820f7f0c7_7EC349D60DB870D61449E7958443756B.jpg" />
    <new />
    <rating system="CSA">
      <value>Tout public</value>
    </rating>
  </programme>
  <programme start="20250703184500" channel="C164.api.telerama.fr" stop="20250703185000">
    <title>Météo 20h00</title>
    <desc lang="fr">Le bulletin météo du soir.</desc>
    <category lang="fr">météo</category>
    <length units="minutes">5</length>
    <icon src="https://focus.telerama.fr/1111x625/2025/02/26/77b8aa883fb34b089662a80507e0c4d1.jpg" />
    <rating system="CSA">
      <value>Tout public</value>
    </rating>
  </programme>
  <programme start="20250703185000" channel="C164.api.telerama.fr" stop="20250703194300">
    <title>Candice Renoir</title>
    <sub-title>Le mensonge cherche toujours à imiter la vérité</sub-title>
    <desc lang="fr">Saison:10 - Episode:3 - Le corps de Mélanie Meyrieux, la quarantaine, est découvert gisant en contrebas d'une carrière, et ce n'est clairement pas un accident. Plusieurs pistes s'offrent à Candice Renoir. L'entreprise de déménagement et de stockage que la victime gérait avec son mari et son beau-frère pourrait bien cacher des activités illicites. L'autre hypothèse et celle d'une dérive dans le milieu scolaire. L'enquête révèle en effet une Mélanie typique du parent intrusif, omniprésent et insupportable. La sagacité de Candice est mise à rude épreuve, mais un cours de conduite pourrait bien s'avérer plus efficace qu'un ADN...</desc>
    <credits>
      <director>Raphaël Lenglet</director>
      <actor>Cécile Bois</actor>
      <actor>Marie Vincent</actor>
      <actor>Raphaël Lenglet</actor>
      <actor>Yeelem Jappain</actor>
      <actor>Renault Brune</actor>
      <actor>Ali Marhyar</actor>
      <actor>François-David Cardonnel</actor>
      <actor>Amélie Robin</actor>
      <actor>Clara Antoons</actor>
      <actor>Olivier Cabassut</actor>
      <actor>Christophe Ntakabanyura</actor>
      <actor>Quentin Michael</actor>
      <writer>Fabienne Facco</writer>
      <writer>Marie-Alice Gadéa</writer>
      <writer>Lionel Moreau</writer>
      <writer>Brigitte Peskine</writer>
      <writer>Robin Barataud</writer>
      <writer>Solen Roy-Pagenault</writer>
    </credits>
    <date>2021</date>
    <category lang="fr">série policière</category>
    <length units="minutes">53</length>
    <icon src="https://focus.telerama.fr/1111x625/2025/02/23/a84ab6ec75a54f4a94a19d2f72c4b115.jpg" />
    <episode-num system="xmltv_ns">9.2.</episode-num>
    <rating system="CSA">
      <value>Tout public</value>
    </rating>
  </programme>
  <programme start="20250703194300" channel="C164.api.telerama.fr" stop="20250703204500">
    <title>Candice Renoir</title>
    <sub-title>Tout ce qui brille n'est pas d'or</sub-title>
    <desc lang="fr">Saison:10 - Episode:4 - Zoé Sénéchal, 15 ans, vient encore de fuguer et cette fois cela fait plus d'une semaine qu'elle est partie. Candice Renoir, qui a bien conscience de tous les dangers qui guettent Zoé dans la rue, fait de cette affaire une priorité. Outre cette enquête, la policière doit aussi négocier un énorme malentendu avec Antoine et faire bonne figure lors d'une cérémonie de remise de médaille alors qu'elle fuit les honneurs plus que tout...</desc>
    <credits>
      <director>Raphaël Lenglet</director>
      <actor>Cécile Bois</actor>
      <actor>Marie Vincent</actor>
      <actor>Raphaël Lenglet</actor>
      <actor>Yeelem Jappain</actor>
      <actor>Ali Marhyar</actor>
      <actor>Clara Antoons</actor>
      <actor>Olivier Cabassut</actor>
      <actor>Christophe Ntakabanyura</actor>
      <actor>Quentin Michael</actor>
      <writer>Fabienne Facco</writer>
      <writer>Pascal Perbet</writer>
      <writer>Brigitte Peskine</writer>
      <writer>Robin Barataud</writer>
      <writer>Solen Roy-Pagenault</writer>
    </credits>
    <date>2021</date>
    <category lang="fr">série policière</category>
    <length units="minutes">62</length>
    <icon src="https://focus.telerama.fr/1111x625/2025/02/23/a84ab6ec75a54f4a94a19d2f72c4b115.jpg" />
    <episode-num system="xmltv_ns">9.3.</episode-num>
    <rating system="CSA">
      <value>Tout public</value>
    </rating>
  </programme>
  <programme start="20250703204500" channel="C164.api.telerama.fr" stop="20250703214600">
    <title>Les 100 lieux qu'il faut voir</title>
    <sub-title>Charente-Maritime</sub-title>
    <desc lang="fr">Saison:1 - Episode:5 - La Charente-Maritime est un département surtout apprécié pour les immenses plages de son littoral long de près de 500 kilomètres. Il bénéficie également d'un patrimoine d'une richesse insoupçonnée, comme le port fortifié de La Rochelle et l'île de Ré, avec ses villages de pierre blanche et ses marais salants. Posé sur l'estuaire de la Gironde, Talmont est une minuscule ville close médiévale, où il fait bon déambuler. Elle fait partie des plus beaux villages de France et était autrefois une étape du chemin de Saint-Jacques de Compostelle.</desc>
    <date>2014</date>
    <category lang="fr">documentaire découvertes</category>
    <length units="minutes">61</length>
    <icon src="https://focus.telerama.fr/1111x625/2025/06/25/cebbf153a7bb42b19f676313e0f9d487.jpg" />
    <episode-num system="xmltv_ns">0.4.</episode-num>
    <rating system="CSA">
      <value>Tout public</value>
    </rating>
  </programme>
  <programme start="20250703214600" channel="C164.api.telerama.fr" stop="20250703221500">
    <title>Destination francophonie</title>
    <sub-title>Destination Nouvelle-Ecosse</sub-title>
    <desc lang="fr">Exploration de la Nouvelle-Ecosse, berceau de l'Acadie. Direction Annapolis Royal, sur les traces des premiers colons français. Dans la région de Clare, rencontre avec une communauté attachée aux traditions francophones. Visite d'un village qui reconstitue le quotidien des Acadiens du XIXe siècle.</desc>
    <category lang="fr">magazine culturel</category>
    <length units="minutes">29</length>
    <icon src="https://focus.telerama.fr/1111x625/2025/06/18/a7e195e1a8634933b6c117a83dc298b0.jpg" />
    <rating system="CSA">
      <value>Tout public</value>
    </rating>
  </programme>
</tv>
