<?xml version='1.0' encoding='UTF-8'?>
<tv>
  <channel id="C111.api.telerama.fr">
    <display-name>Arte</display-name>
    <icon src="https://focus.telerama.fr/500x500/0000/00/01/clear-111.png" />
  </channel>
  <channel id="euronews.rai.it">
    <display-name>EuroNews</display-name>
  </channel>
  <programme start="20251124225500" channel="C111.api.telerama.fr" stop="20251125011000">
    <title>Mystic River</title>
    <desc lang="fr">Jimmy Markum, Sean Divine et Dave Boyle, trois garçonnets, jouent dans une rue calme de Boston. Deux hommes arrivent dans une voiture, et se font passer pour des policiers. Ils emmènent Dave, qui ne réapparaît que quatre jours plus tard, après avoir réussi à s'enfuir de la cave où il était retenu. Leur amitié ne résiste pas à cet événement, et ils perdent contact. Vingt-cinq ans plus tard, un nouveau drame les frappe : Katie, la fille aînée de Jimmy, est retrouvée morte. Sean, devenu policier, est chargé de l'enquête avec son coéquipier, Whitey Powers. Celui-ci en vient rapidement à soupçonner Dave, dont le comportement étrange lui semble suspect...</desc>
    <credits>
      <director>Clint Eastwood</director>
      <actor>Sean Penn</actor>
      <actor>Tim Robbins</actor>
      <actor>Kevin Bacon</actor>
      <actor>Laurence Fishburne</actor>
      <actor>Marcia Gay Harden</actor>
      <actor>Laura Linney</actor>
      <actor>Kevin Chapman</actor>
      <actor>Jason Kelly</actor>
      <actor>Connor Paolo</actor>
      <actor>Cameron Bowen</actor>
      <actor>Emmy Rossum</actor>
      <actor>Tom Guiry</actor>
      <writer>Brian Helgeland</writer>
    </credits>
    <date>2003</date>
    <category lang="fr">film</category>
    <length units="minutes">135</length>
    <icon src="https://focus.telerama.fr/952x634/2025/02/13/1bb3b12cd5094623aedf5d00b3ab0a09.jpg" />
    <country lang="fr">Etats-Unis</country>
    <country lang="fr">Australie</country>
    <video>
      <quality>HDTV</quality>
    </video>
    <previously-shown />
    <subtitles type="teletext">
      <language>fr</language>
    </subtitles>
    <rating system="CSA">
      <value>-12</value>
      <icon src="http://upload.wikimedia.org/wikipedia/commons/thumb/b/bf/Moins12svg/200px-Moins12.svg.png" />
    </rating>
    <star-rating system="Telerama">
      <value>4/5</value>
    </star-rating>
  </programme>
  <programme start="20251125011000" channel="C111.api.telerama.fr" stop="20251125020500">
    <title>La voix de "Born to Be Wild" : John Kay, une icône du rock</title>
    <desc lang="fr">Le titre "Born to Be Wild" reste indissociable du film de Dennis Hopper "Easy Rider", manifeste de la contre-culture américaine sorti en 1969. Mais beaucoup ignorent que la voix grave qui rugit "Fais vrombir ton moteur / Et fonce sur l'autoroute" est celle d'un émigré allemand : Joachim Krauledat, né en 1944 à Tilsit, dans l'actuelle enclave russe de Kaliningrad. Orphelin de père, il grandit à Hanovre après avoir réussi à franchir le rideau de fer avec sa mère, et prend le nom de John Kay à son arrivée à Toronto, en 1958. Sept ans plus tard, le jeune chanteur de blues, malvoyant, y rencontre un autre musicien d'origine allemande, Klaus Karl Kassbaum, qui le recrute dans son groupe The Sparrows. En 1967, ils prennent la route de la Californie où, à grand renfort de LSD, ils vont connaître la gloire en formant Steppenwolf.</desc>
    <category lang="fr">documentaire</category>
    <length units="minutes">55</length>
    <icon src="https://focus.telerama.fr/952x634/2025/11/11/5b9bf1282a94422bb1da1b1d7367a1db.jpg" />
    <country lang="fr">Allemagne</country>
    <video>
      <quality>HDTV</quality>
    </video>
    <previously-shown />
    <premiere />
    <subtitles type="teletext">
      <language>fr</language>
    </subtitles>
    <rating system="CSA">
      <value>Tout public</value>
    </rating>
  </programme>
  <programme start="20251125020500" channel="C111.api.telerama.fr" stop="20251125030000">
    <title>Pierre Cardin : La griffe de la modernité</title>
    <desc lang="fr">Né en Italie en 1922, Pietro Cardin a 2 ans quand ses parents, en quête d'une vie meilleure, s'installent à La Tour-du-Pin, en Isère. Sous l'Occupation, il se fait engager dans un atelier de couture tenu par une ancienne première main de Chanel. La guerre finie, il monte à Paris. Plus rien n'entamera son ascension dans le monde de la haute couture, dont il claque la porte dix ans plus tard pour voler de ses propres ailes, et conquérir la planète en démocratisant sa vision de la mode, qu'il emmène jusqu'à la Chine de Mao et l'URSS de la perestroïka. Autant créateur qu'homme d'affaires, styliste que voyageur, perpétuellement en avance sur son temps, Pierre Cardin est resté jusqu'à sa mort, à 98 ans, à la tête de l'immense empire qu'il a bâti.</desc>
    <category lang="fr">documentaire</category>
    <length units="minutes">55</length>
    <icon src="https://focus.telerama.fr/952x634/2025/11/11/d09ddef2806044caaf71ec4bc2b679c3.jpg" />
    <country lang="fr">France</country>
    <video>
      <quality>HDTV</quality>
    </video>
    <previously-shown />
    <rating system="CSA">
      <value>Tout public</value>
    </rating>
  </programme>
  <programme start="20251125030000" channel="C111.api.telerama.fr" stop="20251125032600">
    <title>Les maîtres des abeilles</title>
    <desc lang="fr">Saison:1 - Episode:7 - Des apiculteurs mayas ont décidé, il y a vingt ans, de sauver l'abeille mélipone, un insecte autochtone, sans dard. Ils ont ainsi réveillé un savoir-faire ancestral.</desc>
    <credits>
      <director>François Chayé</director>
    </credits>
    <date>2017</date>
    <category lang="fr">documentaire</category>
    <length units="minutes">26</length>
    <icon src="https://focus.telerama.fr/952x634/2025/10/17/9a9406b7d9a64768bc89b347133d7a92.jpg" />
    <country lang="fr">France</country>
    <episode-num system="xmltv_ns">0.6.</episode-num>
    <video>
      <quality>HDTV</quality>
    </video>
    <previously-shown />
    <subtitles type="teletext">
      <language>fr</language>
    </subtitles>
    <rating system="CSA">
      <value>Tout public</value>
    </rating>
  </programme>
  <programme start="20251125032600" channel="C111.api.telerama.fr" stop="20251125040000">
    <title>Pause</title>
    <credits>
      <presenter>Jean-Michel Zecca</presenter>
    </credits>
    <category lang="fr">autre</category>
    <length units="minutes">34</length>
    <icon src="https://focus.telerama.fr/952x634/2021/06/09/70e696282107b49d230702cd59c274cd5f627080.jpg" />
    <rating system="CSA">
      <value>Tout public</value>
    </rating>
  </programme>
  <programme start="20251125040000" channel="C111.api.telerama.fr" stop="20251125042500">
    <title>Médecines d'ailleurs</title>
    <desc lang="fr">Saison:2 - Episode:20 - Au Malawi, les guérisseurs sont guidés par un souci d'adaptation et d'intégration : Kachepa Bulumeni et son assistante veillent à la santé des habitants isolés.</desc>
    <credits>
      <director>Frédéric Febvre</director>
    </credits>
    <date>2015</date>
    <category lang="fr">documentaire</category>
    <length units="minutes">25</length>
    <icon src="https://focus.telerama.fr/952x634/2025/06/19/287b32e0ac044a318d368c79becf1e6e.jpg" />
    <country lang="fr">France</country>
    <episode-num system="xmltv_ns">1.19.</episode-num>
    <video>
      <quality>HDTV</quality>
    </video>
    <previously-shown />
    <subtitles type="teletext">
      <language>fr</language>
    </subtitles>
    <rating system="CSA">
      <value>Tout public</value>
    </rating>
  </programme>
  <programme start="20251125042500" channel="C111.api.telerama.fr" stop="20251125045500">
    <title>Médecines d'ailleurs</title>
    <desc lang="fr">Saison:2 - Episode:4 - Au Yucatan, Bernard Fontanille rencontre don Galo, médecin traditionnel qui fait partie de la catégorie la plus élevée des soignants : les H'men.</desc>
    <credits>
      <director>Nicos Argillet</director>
    </credits>
    <date>2015</date>
    <category lang="fr">documentaire</category>
    <length units="minutes">30</length>
    <icon src="https://focus.telerama.fr/952x634/2025/06/21/108b3f54a4d04412ba81da6bb7be064c.jpg" />
    <country lang="fr">France</country>
    <episode-num system="xmltv_ns">1.3.</episode-num>
    <video>
      <quality>HDTV</quality>
    </video>
    <previously-shown />
    <subtitles type="teletext">
      <language>fr</language>
    </subtitles>
    <rating system="CSA">
      <value>Tout public</value>
    </rating>
  </programme>
  <programme start="20251125045500" channel="C111.api.telerama.fr" stop="20251125052500">
    <title>Berlin : des retraitées turques en voyage</title>
    <desc lang="fr">Arrivée en RFA durant l'enfance, la première génération d'immigrés turcs a aujourd'hui atteint l'âge de la retraite. À Berlin, un groupe de femmes seniors profite de cette liberté nouvelle pour enfin découvrir l'Allemagne. Après avoir passé leur vie à travailler, elles sont bien décidées à voyager aussi longtemps que possible.</desc>
    <category lang="fr">documentaire</category>
    <length units="minutes">30</length>
    <icon src="https://focus.telerama.fr/952x634/2025/11/11/6629b64c71c640be9d86a49ce1e16705.jpg" />
    <country lang="fr">Allemagne</country>
    <video>
      <quality>HDTV</quality>
    </video>
    <previously-shown />
    <rating system="CSA">
      <value>Tout public</value>
    </rating>
  </programme>
  <programme start="20251124225500" channel="C111.api.telerama.fr" stop="20251125011000">
    <title>Mystic River</title>
    <desc lang="fr">Jimmy Markum, Sean Divine et Dave Boyle, trois garçonnets, jouent dans une rue calme de Boston. Deux hommes arrivent dans une voiture, et se font passer pour des policiers. Ils emmènent Dave, qui ne réapparaît que quatre jours plus tard, après avoir réussi à s'enfuir de la cave où il était retenu. Leur amitié ne résiste pas à cet événement, et ils perdent contact. Vingt-cinq ans plus tard, un nouveau drame les frappe : Katie, la fille aînée de Jimmy, est retrouvée morte. Sean, devenu policier, est chargé de l'enquête avec son coéquipier, Whitey Powers. Celui-ci en vient rapidement à soupçonner Dave, dont le comportement étrange lui semble suspect...</desc>
    <credits>
      <director>Clint Eastwood</director>
      <actor>Sean Penn</actor>
      <actor>Tim Robbins</actor>
      <actor>Kevin Bacon</actor>
      <actor>Laurence Fishburne</actor>
      <actor>Marcia Gay Harden</actor>
      <actor>Laura Linney</actor>
      <actor>Kevin Chapman</actor>
      <actor>Jason Kelly</actor>
      <actor>Connor Paolo</actor>
      <actor>Cameron Bowen</actor>
      <actor>Emmy Rossum</actor>
      <actor>Tom Guiry</actor>
      <writer>Brian Helgeland</writer>
    </credits>
    <date>2003</date>
    <category lang="fr">film</category>
    <length units="minutes">135</length>
    <icon src="https://focus.telerama.fr/952x634/2025/02/13/1bb3b12cd5094623aedf5d00b3ab0a09.jpg" />
    <country lang="fr">Etats-Unis</country>
    <country lang="fr">Australie</country>
    <video>
      <quality>HDTV</quality>
    </video>
    <previously-shown />
    <subtitles type="teletext">
      <language>fr</language>
    </subtitles>
    <rating system="CSA">
      <value>-12</value>
      <icon src="http://upload.wikimedia.org/wikipedia/commons/thumb/b/bf/Moins12svg/200px-Moins12.svg.png" />
    </rating>
    <star-rating system="Telerama">
      <value>4/5</value>
    </star-rating>
  </programme>
  <programme start="20251125011000" channel="C111.api.telerama.fr" stop="20251125020500">
    <title>La voix de "Born to Be Wild" : John Kay, une icône du rock</title>
    <desc lang="fr">Le titre "Born to Be Wild" reste indissociable du film de Dennis Hopper "Easy Rider", manifeste de la contre-culture américaine sorti en 1969. Mais beaucoup ignorent que la voix grave qui rugit "Fais vrombir ton moteur / Et fonce sur l'autoroute" est celle d'un émigré allemand : Joachim Krauledat, né en 1944 à Tilsit, dans l'actuelle enclave russe de Kaliningrad. Orphelin de père, il grandit à Hanovre après avoir réussi à franchir le rideau de fer avec sa mère, et prend le nom de John Kay à son arrivée à Toronto, en 1958. Sept ans plus tard, le jeune chanteur de blues, malvoyant, y rencontre un autre musicien d'origine allemande, Klaus Karl Kassbaum, qui le recrute dans son groupe The Sparrows. En 1967, ils prennent la route de la Californie où, à grand renfort de LSD, ils vont connaître la gloire en formant Steppenwolf.</desc>
    <category lang="fr">documentaire</category>
    <length units="minutes">55</length>
    <icon src="https://focus.telerama.fr/952x634/2025/11/11/5b9bf1282a94422bb1da1b1d7367a1db.jpg" />
    <country lang="fr">Allemagne</country>
    <video>
      <quality>HDTV</quality>
    </video>
    <previously-shown />
    <premiere />
    <subtitles type="teletext">
      <language>fr</language>
    </subtitles>
    <rating system="CSA">
      <value>Tout public</value>
    </rating>
  </programme>
  <programme start="20251125020500" channel="C111.api.telerama.fr" stop="20251125030000">
    <title>Pierre Cardin : La griffe de la modernité</title>
    <desc lang="fr">Né en Italie en 1922, Pietro Cardin a 2 ans quand ses parents, en quête d'une vie meilleure, s'installent à La Tour-du-Pin, en Isère. Sous l'Occupation, il se fait engager dans un atelier de couture tenu par une ancienne première main de Chanel. La guerre finie, il monte à Paris. Plus rien n'entamera son ascension dans le monde de la haute couture, dont il claque la porte dix ans plus tard pour voler de ses propres ailes, et conquérir la planète en démocratisant sa vision de la mode, qu'il emmène jusqu'à la Chine de Mao et l'URSS de la perestroïka. Autant créateur qu'homme d'affaires, styliste que voyageur, perpétuellement en avance sur son temps, Pierre Cardin est resté jusqu'à sa mort, à 98 ans, à la tête de l'immense empire qu'il a bâti.</desc>
    <category lang="fr">documentaire</category>
    <length units="minutes">55</length>
    <icon src="https://focus.telerama.fr/952x634/2025/11/11/d09ddef2806044caaf71ec4bc2b679c3.jpg" />
    <country lang="fr">France</country>
    <video>
      <quality>HDTV</quality>
    </video>
    <previously-shown />
    <rating system="CSA">
      <value>Tout public</value>
    </rating>
  </programme>
  <programme start="20251125030000" channel="C111.api.telerama.fr" stop="20251125032600">
    <title>Les maîtres des abeilles</title>
    <desc lang="fr">Saison:1 - Episode:7 - Des apiculteurs mayas ont décidé, il y a vingt ans, de sauver l'abeille mélipone, un insecte autochtone, sans dard. Ils ont ainsi réveillé un savoir-faire ancestral.</desc>
    <credits>
      <director>François Chayé</director>
    </credits>
    <date>2017</date>
    <category lang="fr">documentaire</category>
    <length units="minutes">26</length>
    <icon src="https://focus.telerama.fr/952x634/2025/10/17/9a9406b7d9a64768bc89b347133d7a92.jpg" />
    <country lang="fr">France</country>
    <episode-num system="xmltv_ns">0.6.</episode-num>
    <video>
      <quality>HDTV</quality>
    </video>
    <previously-shown />
    <subtitles type="teletext">
      <language>fr</language>
    </subtitles>
    <rating system="CSA">
      <value>Tout public</value>
    </rating>
  </programme>
  <programme start="20251125032600" channel="C111.api.telerama.fr" stop="20251125040000">
    <title>Pause</title>
    <credits>
      <presenter>Jean-Michel Zecca</presenter>
    </credits>
    <category lang="fr">autre</category>
    <length units="minutes">34</length>
    <icon src="https://focus.telerama.fr/952x634/2021/06/09/70e696282107b49d230702cd59c274cd5f627080.jpg" />
    <rating system="CSA">
      <value>Tout public</value>
    </rating>
  </programme>
  <programme start="20251125040000" channel="C111.api.telerama.fr" stop="20251125042500">
    <title>Médecines d'ailleurs</title>
    <desc lang="fr">Saison:2 - Episode:20 - Au Malawi, les guérisseurs sont guidés par un souci d'adaptation et d'intégration : Kachepa Bulumeni et son assistante veillent à la santé des habitants isolés.</desc>
    <credits>
      <director>Frédéric Febvre</director>
    </credits>
    <date>2015</date>
    <category lang="fr">documentaire</category>
    <length units="minutes">25</length>
    <icon src="https://focus.telerama.fr/952x634/2025/06/19/287b32e0ac044a318d368c79becf1e6e.jpg" />
    <country lang="fr">France</country>
    <episode-num system="xmltv_ns">1.19.</episode-num>
    <video>
      <quality>HDTV</quality>
    </video>
    <previously-shown />
    <subtitles type="teletext">
      <language>fr</language>
    </subtitles>
    <rating system="CSA">
      <value>Tout public</value>
    </rating>
  </programme>
  <programme start="20251125042500" channel="C111.api.telerama.fr" stop="20251125045500">
    <title>Médecines d'ailleurs</title>
    <desc lang="fr">Saison:2 - Episode:4 - Au Yucatan, Bernard Fontanille rencontre don Galo, médecin traditionnel qui fait partie de la catégorie la plus élevée des soignants : les H'men.</desc>
    <credits>
      <director>Nicos Argillet</director>
    </credits>
    <date>2015</date>
    <category lang="fr">documentaire</category>
    <length units="minutes">30</length>
    <icon src="https://focus.telerama.fr/952x634/2025/06/21/108b3f54a4d04412ba81da6bb7be064c.jpg" />
    <country lang="fr">France</country>
    <episode-num system="xmltv_ns">1.3.</episode-num>
    <video>
      <quality>HDTV</quality>
    </video>
    <previously-shown />
    <subtitles type="teletext">
      <language>fr</language>
    </subtitles>
    <rating system="CSA">
      <value>Tout public</value>
    </rating>
  </programme>
  <programme start="20251125045500" channel="C111.api.telerama.fr" stop="20251125052500">
    <title>Berlin : des retraitées turques en voyage</title>
    <desc lang="fr">Arrivée en RFA durant l'enfance, la première génération d'immigrés turcs a aujourd'hui atteint l'âge de la retraite. À Berlin, un groupe de femmes seniors profite de cette liberté nouvelle pour enfin découvrir l'Allemagne. Après avoir passé leur vie à travailler, elles sont bien décidées à voyager aussi longtemps que possible.</desc>
    <category lang="fr">documentaire</category>
    <length units="minutes">30</length>
    <icon src="https://focus.telerama.fr/952x634/2025/11/11/6629b64c71c640be9d86a49ce1e16705.jpg" />
    <country lang="fr">Allemagne</country>
    <video>
      <quality>HDTV</quality>
    </video>
    <previously-shown />
    <rating system="CSA">
      <value>Tout public</value>
    </rating>
  </programme>
</tv>
