<?xml version='1.0' encoding='UTF-8'?>
<tv>
  <channel id="C111.api.telerama.fr">
    <display-name>Arte</display-name>
    <icon src="https://focus.telerama.fr/500x500/0000/00/01/clear-111.png" />
  </channel>
  <channel id="euronews.rai.it">
    <display-name>EuroNews</display-name>
  </channel>
  <programme start="20251217233000 +0100" channel="C111.api.telerama.fr" stop="20251218011000 +0100">
    <title>La Ligne</title>
    <desc lang="fr">Après avoir violemment agressé sa mère, Margaret, 35 ans, doit respecter une mesure d'éloignement, dans l'attente de son jugement. Interdite d'entrer en contact avec cette dernière et de s'approcher à moins de cent mètres de la maison où elle vit, Margaret subit cette décision comme une totale injustice, mais tente tant bien que mal de la respecter. La jeune femme finit pourtant par céder à ses démons, incapable de rester plus longtemps éloignée des siens. Chaque jour, elle se rapproche un peu plus de cette barrière qui, une fois franchie, pourrait l'envoyer derrière les barreaux...</desc>
    <credits>
      <director>Ursula Meier</director>
      <actor>Stéphanie Blanchoud</actor>
      <actor>Valeria Tedeschi</actor>
      <actor>Dali Benssalah</actor>
      <actor>Benjamin Biolay</actor>
      <actor>India Hair</actor>
      <actor>Elli Spagnolo</actor>
      <actor>Eric Ruf</actor>
      <actor>Jean-François Stévenin</actor>
      <actor>Thomas Wiesel</actor>
      <actor>Louis Gence</actor>
      <actor>Jean Leclerc</actor>
      <actor>Thierry Romanens</actor>
      <writer>Stéphanie Blanchoud</writer>
      <writer>Ursula Meier</writer>
      <writer>Antoine Jaccoud</writer>
    </credits>
    <date>2023</date>
    <category lang="fr">film</category>
    <length units="minutes">100</length>
    <icon src="https://focus.telerama.fr/952x634/2025/03/05/ed0ec93be4764bcb9fe48edf3ffc4d0a.jpg" />
    <country lang="fr">France</country>
    <country lang="fr">Belgique</country>
    <country lang="fr">Suisse</country>
    <video>
      <quality>HDTV</quality>
    </video>
    <previously-shown />
    <premiere />
    <subtitles type="teletext">
      <language>fr</language>
    </subtitles>
    <rating system="CSA">
      <value>Tout public</value>
    </rating>
    <star-rating system="Telerama">
      <value>3/5</value>
    </star-rating>
  </programme>
  <programme start="20251218011000 +0100" channel="C111.api.telerama.fr" stop="20251218024000 +0100">
    <title>Douce nuit, folle nuit</title>
    <desc lang="fr">Infirmier épuisé après une nuit de garde, Omar se met en quête d'un sapin pour sa famille. Mais tout semble se liguer contre lui, jusqu'à la voisine et son chien. Rosi reçoit la visite surprise de son père après plusieurs années d'absence, un vieux monsieur vacillant d'alcool et de chagrin, qui se surprend à jouer au grand-père modèle avec sa petite-fille Pepi. Pendant ce temps, Koharu, la petite amie de Simon, décide de concocter un menu de réveillon un peu spécial, destiné à rabattre le caquet de ses beaux-parents racistes. Le livreur Vlad, père Noël des temps modernes, se retrouve quant à lui coincé dans un ascenseur. Un véritable dialogue de sourds s'engage alors avec les habitants de l'immeuble.</desc>
    <credits>
      <director>Arash T. Riahi</director>
      <director>Arman T. Riahi</director>
      <director>Mirjam Unger</director>
      <actor>Faris Rahoma</actor>
      <actor>Inge Maux</actor>
      <actor>Roland Düringer</actor>
      <actor>Kathrin Resetarits</actor>
      <actor>Lukas Resetarits</actor>
      <actor>Maya Unger</actor>
      <actor>Sonja Chan</actor>
      <actor>Ferdinand Seebacher</actor>
      <actor>Susi Stach</actor>
      <actor>Dietrich Siegl</actor>
      <actor>Aleksandar Petrović</actor>
      <actor>Maddalena Hirschal</actor>
    </credits>
    <category lang="fr">telefilm</category>
    <length units="minutes">90</length>
    <icon src="https://focus.telerama.fr/952x634/2025/12/04/f7ed509873b74b5d8609a0df3288a494.jpg" />
    <country lang="fr">Autriche</country>
    <video>
      <quality>HDTV</quality>
    </video>
    <previously-shown />
    <rating system="CSA">
      <value>Tout public</value>
    </rating>
  </programme>
  <programme start="20251218024000 +0100" channel="C111.api.telerama.fr" stop="20251218031500 +0100">
    <title>La Grèce d'île en île</title>
    <desc lang="fr">Un voyage à la pointe sud-est de l'Adriatique, de Corfou, avec ses traditions pascales uniques, à Paxos et Anipaxos, avant de mettre le cap vers Ithaque.</desc>
    <credits>
      <director>Dennis Wells</director>
      <director>Sandra Papadopoulos</director>
      <director>Johannes Backes</director>
      <writer>Johannes Backes</writer>
      <writer>Dennis Wells</writer>
    </credits>
    <category lang="fr">documentaire</category>
    <length units="minutes">35</length>
    <icon src="https://focus.telerama.fr/952x634/2025/12/04/00b91960149547259dc458f53c7f3ec6.jpg" />
    <country lang="fr">Allemagne</country>
    <video>
      <quality>HDTV</quality>
    </video>
    <previously-shown />
    <rating system="CSA">
      <value>Tout public</value>
    </rating>
  </programme>
  <programme start="20251218031500 +0100" channel="C111.api.telerama.fr" stop="20251218041000 +0100">
    <title>A Symphony of Noise : une révolution sonore selon Matthew Herbert</title>
    <desc lang="fr">Portrait de l'artiste britannique Matthew Herbert, expérimentateur excentrique qui compose de la musique à partir des moindres sons du quotidien.</desc>
    <category lang="fr">documentaire</category>
    <length units="minutes">55</length>
    <icon src="https://focus.telerama.fr/952x634/2025/12/04/7edd0cc3d79442f8ab75627d0d7a458e.jpg" />
    <country lang="fr">Allemagne</country>
    <video>
      <quality>HDTV</quality>
    </video>
    <previously-shown />
    <rating system="CSA">
      <value>Tout public</value>
    </rating>
  </programme>
  <programme start="20251218041000 +0100" channel="C111.api.telerama.fr" stop="20251218043500 +0100">
    <title>Médecines d'ailleurs</title>
    <desc lang="fr">Saison:2 - Episode:7 - Pour contourner les distances et les reliefs, c'est par le ciel que les secours arrivent. Des bases d'où peuvent décoller les hélicoptères émaillent tout le territoire australien.</desc>
    <credits>
      <director>Laurent Sardi</director>
    </credits>
    <date>2015</date>
    <category lang="fr">documentaire</category>
    <length units="minutes">25</length>
    <icon src="https://focus.telerama.fr/952x634/2025/06/27/fca4bf292b0e46f0b82e209a1f47f596.jpg" />
    <country lang="fr">France</country>
    <episode-num system="xmltv_ns">1.6.</episode-num>
    <video>
      <quality>HDTV</quality>
    </video>
    <previously-shown />
    <subtitles type="teletext">
      <language>fr</language>
    </subtitles>
    <rating system="CSA">
      <value>Tout public</value>
    </rating>
  </programme>
  <programme start="20251218043500 +0100" channel="C111.api.telerama.fr" stop="20251218050000 +0100">
    <title>Pause</title>
    <credits>
      <presenter>Jean-Michel Zecca</presenter>
    </credits>
    <category lang="fr">autre</category>
    <length units="minutes">25</length>
    <icon src="https://focus.telerama.fr/952x634/2021/06/09/70e696282107b49d230702cd59c274cd5f627080.jpg" />
    <rating system="CSA">
      <value>Tout public</value>
    </rating>
  </programme>
  <programme start="20251218050000 +0100" channel="C111.api.telerama.fr" stop="20251218055500 +0100">
    <title>La santé des femmes : De l'ignorance à la reconnaissance</title>
    <desc lang="fr">Longtemps dominé par les hommes, le monde de la médecine continue d'ériger en norme le corps masculin : que ce soit dans la recherche, dans l'enseignement universitaire ou dans la pratique quotidienne, les différences physiologiques liées au sexe - et à des facteurs génétiques, hormonaux ou métaboliques - sont encore mal connues et trop peu prises en compte. Les médecins tendent par ailleurs à minimiser certains symptômes comme la douleur, lorsqu'ils sont décrits par des femmes. Des points aveugles de la pratique médicale qui peuvent conduire à des diagnostics erronés ou retardés, notamment pour certaines maladies comme l'endométriose. Passé le diagnostic, il arrive également que les traitements prescrits s'avèrent inadaptés au corps féminin, qui réagit différemment à certains médicaments.</desc>
    <credits>
      <director>Ursula Duplantier</director>
      <director>Marta Schröer</director>
    </credits>
    <category lang="fr">documentaire</category>
    <length units="minutes">55</length>
    <icon src="https://focus.telerama.fr/952x634/2025/12/05/901385a8421a4422be0473c828eedf91.jpg" />
    <country lang="fr">Allemagne</country>
    <video>
      <quality>HDTV</quality>
    </video>
    <previously-shown />
    <subtitles type="teletext">
      <language>fr</language>
    </subtitles>
    <rating system="CSA">
      <value>Tout public</value>
    </rating>
    <star-rating system="Telerama">
      <value>4/5</value>
    </star-rating>
  </programme>
  <programme start="20251218055500 +0100" channel="C111.api.telerama.fr" stop="20251218063000 +0100">
    <title>Croatie : les derniers gardiens de phare</title>
    <desc lang="fr">Palagruža, un rocher isolé surmonté d'un phare habité depuis 1875, se dresse au milieu de la mer Adriatique. Vojo Šain, l'un des derniers gardiens de phare de Croatie, y travaille depuis 26 ans. Cette île est bien plus qu'un simple lieu de travail, c'est son second foyer. Des semaines durant, il vit sans confort et à l'écart de la civilisation.</desc>
    <category lang="fr">documentaire</category>
    <length units="minutes">35</length>
    <icon src="https://focus.telerama.fr/952x634/2025/12/04/0909403089aa46de95d356e8976e034a.jpg" />
    <country lang="fr">Allemagne</country>
    <video>
      <quality>HDTV</quality>
    </video>
    <previously-shown />
    <rating system="CSA">
      <value>Tout public</value>
    </rating>
  </programme>
  <programme start="20251217233000 +0100" channel="C111.api.telerama.fr" stop="20251218011000 +0100">
    <title>La Ligne</title>
    <desc lang="fr">Après avoir violemment agressé sa mère, Margaret, 35 ans, doit respecter une mesure d'éloignement, dans l'attente de son jugement. Interdite d'entrer en contact avec cette dernière et de s'approcher à moins de cent mètres de la maison où elle vit, Margaret subit cette décision comme une totale injustice, mais tente tant bien que mal de la respecter. La jeune femme finit pourtant par céder à ses démons, incapable de rester plus longtemps éloignée des siens. Chaque jour, elle se rapproche un peu plus de cette barrière qui, une fois franchie, pourrait l'envoyer derrière les barreaux...</desc>
    <credits>
      <director>Ursula Meier</director>
      <actor>Stéphanie Blanchoud</actor>
      <actor>Valeria Tedeschi</actor>
      <actor>Dali Benssalah</actor>
      <actor>Benjamin Biolay</actor>
      <actor>India Hair</actor>
      <actor>Elli Spagnolo</actor>
      <actor>Eric Ruf</actor>
      <actor>Jean-François Stévenin</actor>
      <actor>Thomas Wiesel</actor>
      <actor>Louis Gence</actor>
      <actor>Jean Leclerc</actor>
      <actor>Thierry Romanens</actor>
      <writer>Stéphanie Blanchoud</writer>
      <writer>Ursula Meier</writer>
      <writer>Antoine Jaccoud</writer>
    </credits>
    <date>2023</date>
    <category lang="fr">film</category>
    <length units="minutes">100</length>
    <icon src="https://focus.telerama.fr/952x634/2025/03/05/ed0ec93be4764bcb9fe48edf3ffc4d0a.jpg" />
    <country lang="fr">France</country>
    <country lang="fr">Belgique</country>
    <country lang="fr">Suisse</country>
    <video>
      <quality>HDTV</quality>
    </video>
    <previously-shown />
    <premiere />
    <subtitles type="teletext">
      <language>fr</language>
    </subtitles>
    <rating system="CSA">
      <value>Tout public</value>
    </rating>
    <star-rating system="Telerama">
      <value>3/5</value>
    </star-rating>
  </programme>
  <programme start="20251218011000 +0100" channel="C111.api.telerama.fr" stop="20251218024000 +0100">
    <title>Douce nuit, folle nuit</title>
    <desc lang="fr">Infirmier épuisé après une nuit de garde, Omar se met en quête d'un sapin pour sa famille. Mais tout semble se liguer contre lui, jusqu'à la voisine et son chien. Rosi reçoit la visite surprise de son père après plusieurs années d'absence, un vieux monsieur vacillant d'alcool et de chagrin, qui se surprend à jouer au grand-père modèle avec sa petite-fille Pepi. Pendant ce temps, Koharu, la petite amie de Simon, décide de concocter un menu de réveillon un peu spécial, destiné à rabattre le caquet de ses beaux-parents racistes. Le livreur Vlad, père Noël des temps modernes, se retrouve quant à lui coincé dans un ascenseur. Un véritable dialogue de sourds s'engage alors avec les habitants de l'immeuble.</desc>
    <credits>
      <director>Arash T. Riahi</director>
      <director>Arman T. Riahi</director>
      <director>Mirjam Unger</director>
      <actor>Faris Rahoma</actor>
      <actor>Inge Maux</actor>
      <actor>Roland Düringer</actor>
      <actor>Kathrin Resetarits</actor>
      <actor>Lukas Resetarits</actor>
      <actor>Maya Unger</actor>
      <actor>Sonja Chan</actor>
      <actor>Ferdinand Seebacher</actor>
      <actor>Susi Stach</actor>
      <actor>Dietrich Siegl</actor>
      <actor>Aleksandar Petrović</actor>
      <actor>Maddalena Hirschal</actor>
    </credits>
    <category lang="fr">telefilm</category>
    <length units="minutes">90</length>
    <icon src="https://focus.telerama.fr/952x634/2025/12/04/f7ed509873b74b5d8609a0df3288a494.jpg" />
    <country lang="fr">Autriche</country>
    <video>
      <quality>HDTV</quality>
    </video>
    <previously-shown />
    <rating system="CSA">
      <value>Tout public</value>
    </rating>
  </programme>
  <programme start="20251218024000 +0100" channel="C111.api.telerama.fr" stop="20251218031500 +0100">
    <title>La Grèce d'île en île</title>
    <desc lang="fr">Un voyage à la pointe sud-est de l'Adriatique, de Corfou, avec ses traditions pascales uniques, à Paxos et Anipaxos, avant de mettre le cap vers Ithaque.</desc>
    <credits>
      <director>Dennis Wells</director>
      <director>Sandra Papadopoulos</director>
      <director>Johannes Backes</director>
      <writer>Johannes Backes</writer>
      <writer>Dennis Wells</writer>
    </credits>
    <category lang="fr">documentaire</category>
    <length units="minutes">35</length>
    <icon src="https://focus.telerama.fr/952x634/2025/12/04/00b91960149547259dc458f53c7f3ec6.jpg" />
    <country lang="fr">Allemagne</country>
    <video>
      <quality>HDTV</quality>
    </video>
    <previously-shown />
    <rating system="CSA">
      <value>Tout public</value>
    </rating>
  </programme>
  <programme start="20251218031500 +0100" channel="C111.api.telerama.fr" stop="20251218041000 +0100">
    <title>A Symphony of Noise : une révolution sonore selon Matthew Herbert</title>
    <desc lang="fr">Portrait de l'artiste britannique Matthew Herbert, expérimentateur excentrique qui compose de la musique à partir des moindres sons du quotidien.</desc>
    <category lang="fr">documentaire</category>
    <length units="minutes">55</length>
    <icon src="https://focus.telerama.fr/952x634/2025/12/04/7edd0cc3d79442f8ab75627d0d7a458e.jpg" />
    <country lang="fr">Allemagne</country>
    <video>
      <quality>HDTV</quality>
    </video>
    <previously-shown />
    <rating system="CSA">
      <value>Tout public</value>
    </rating>
  </programme>
  <programme start="20251218041000 +0100" channel="C111.api.telerama.fr" stop="20251218043500 +0100">
    <title>Médecines d'ailleurs</title>
    <desc lang="fr">Saison:2 - Episode:7 - Pour contourner les distances et les reliefs, c'est par le ciel que les secours arrivent. Des bases d'où peuvent décoller les hélicoptères émaillent tout le territoire australien.</desc>
    <credits>
      <director>Laurent Sardi</director>
    </credits>
    <date>2015</date>
    <category lang="fr">documentaire</category>
    <length units="minutes">25</length>
    <icon src="https://focus.telerama.fr/952x634/2025/06/27/fca4bf292b0e46f0b82e209a1f47f596.jpg" />
    <country lang="fr">France</country>
    <episode-num system="xmltv_ns">1.6.</episode-num>
    <video>
      <quality>HDTV</quality>
    </video>
    <previously-shown />
    <subtitles type="teletext">
      <language>fr</language>
    </subtitles>
    <rating system="CSA">
      <value>Tout public</value>
    </rating>
  </programme>
  <programme start="20251218043500 +0100" channel="C111.api.telerama.fr" stop="20251218050000 +0100">
    <title>Pause</title>
    <credits>
      <presenter>Jean-Michel Zecca</presenter>
    </credits>
    <category lang="fr">autre</category>
    <length units="minutes">25</length>
    <icon src="https://focus.telerama.fr/952x634/2021/06/09/70e696282107b49d230702cd59c274cd5f627080.jpg" />
    <rating system="CSA">
      <value>Tout public</value>
    </rating>
  </programme>
  <programme start="20251218050000 +0100" channel="C111.api.telerama.fr" stop="20251218055500 +0100">
    <title>La santé des femmes : De l'ignorance à la reconnaissance</title>
    <desc lang="fr">Longtemps dominé par les hommes, le monde de la médecine continue d'ériger en norme le corps masculin : que ce soit dans la recherche, dans l'enseignement universitaire ou dans la pratique quotidienne, les différences physiologiques liées au sexe - et à des facteurs génétiques, hormonaux ou métaboliques - sont encore mal connues et trop peu prises en compte. Les médecins tendent par ailleurs à minimiser certains symptômes comme la douleur, lorsqu'ils sont décrits par des femmes. Des points aveugles de la pratique médicale qui peuvent conduire à des diagnostics erronés ou retardés, notamment pour certaines maladies comme l'endométriose. Passé le diagnostic, il arrive également que les traitements prescrits s'avèrent inadaptés au corps féminin, qui réagit différemment à certains médicaments.</desc>
    <credits>
      <director>Ursula Duplantier</director>
      <director>Marta Schröer</director>
    </credits>
    <category lang="fr">documentaire</category>
    <length units="minutes">55</length>
    <icon src="https://focus.telerama.fr/952x634/2025/12/05/901385a8421a4422be0473c828eedf91.jpg" />
    <country lang="fr">Allemagne</country>
    <video>
      <quality>HDTV</quality>
    </video>
    <previously-shown />
    <subtitles type="teletext">
      <language>fr</language>
    </subtitles>
    <rating system="CSA">
      <value>Tout public</value>
    </rating>
    <star-rating system="Telerama">
      <value>4/5</value>
    </star-rating>
  </programme>
  <programme start="20251218055500 +0100" channel="C111.api.telerama.fr" stop="20251218063000 +0100">
    <title>Croatie : les derniers gardiens de phare</title>
    <desc lang="fr">Palagruža, un rocher isolé surmonté d'un phare habité depuis 1875, se dresse au milieu de la mer Adriatique. Vojo Šain, l'un des derniers gardiens de phare de Croatie, y travaille depuis 26 ans. Cette île est bien plus qu'un simple lieu de travail, c'est son second foyer. Des semaines durant, il vit sans confort et à l'écart de la civilisation.</desc>
    <category lang="fr">documentaire</category>
    <length units="minutes">35</length>
    <icon src="https://focus.telerama.fr/952x634/2025/12/04/0909403089aa46de95d356e8976e034a.jpg" />
    <country lang="fr">Allemagne</country>
    <video>
      <quality>HDTV</quality>
    </video>
    <previously-shown />
    <rating system="CSA">
      <value>Tout public</value>
    </rating>
  </programme>
</tv>
